{"lastUsed":1773660335820,"path":"C:\/Users\/knguy139\/Documents\/Projects","projectCount":11,"recentFiles":[{"path":"\/MBM Therapies\/Scripts","parentWorkspace":"C:\/Users\/knguy139\/Documents\/Projects","name":"Therapy_PMPM+VpE_202601.sql","lastModified":1773660343901,"locationURI":"file:\/C:\/Users\/knguy139\/Documents\/Projects\/MBM%20Therapies\/Scripts\/Therapy_PMPM+VpE_202601.sql"},{"path":"\/MBM Therapies\/Scripts","parentWorkspace":"C:\/Users\/knguy139\/Documents\/Projects","name":"Therapy_Savings_202602_Snowflake_stable.sql","lastModified":1773431333578,"locationURI":"file:\/C:\/Users\/knguy139\/Documents\/Projects\/MBM%20Therapies\/Scripts\/Therapy_Savings_202602_Snowflake_stable.sql"},{"path":"\/MBM Therapies\/Scripts","parentWorkspace":"C:\/Users\/knguy139\/Documents\/Projects","name":"therapy_medsupp.sql","lastModified":1773342840239,"locationURI":"file:\/C:\/Users\/knguy139\/Documents\/Projects\/MBM%20Therapies\/Scripts\/therapy_medsupp.sql"},{"path":"\/MBM Therapies\/Scripts","parentWorkspace":"C:\/Users\/knguy139\/Documents\/Projects","name":"Therapies_LOPAcount_wEverLOPA_202511.sql","lastModified":1772675436460,"locationURI":"file:\/C:\/Users\/knguy139\/Documents\/Projects\/MBM%20Therapies\/Scripts\/Therapies_LOPAcount_wEverLOPA_202511.sql"},{"path":"\/MBM Therapies\/Scripts","parentWorkspace":"C:\/Users\/knguy139\/Documents\/Projects","name":"MBM_cpbp_check.sql","lastModified":1773346670917,"locationURI":"file:\/C:\/Users\/knguy139\/Documents\/Projects\/MBM%20Therapies\/Scripts\/MBM_cpbp_check.sql"}]}